download_npo/__init__.py
download_npo/cli.py
download_npo/gui.py
download_npo/init_test.py
download_npo/listing.py
download_npo/mms.py
download_npo/sites.py
download_npo/sites_test.py
download_npo-2.9.1.data/data/share/applications/download-npo-gui.desktop
download_npo-2.9.1.data/data/share/doc/download-npo/README.markdown
download_npo-2.9.1.data/data/share/download-npo/icon.gif
download_npo-2.9.1.data/data/share/download-npo/icon.svg
download_npo-2.9.1.data/scripts/download-npo
download_npo-2.9.1.data/scripts/download-npo-gui
download_npo-2.9.1.data/scripts/play-npo
usr/share/icons/hicolor/scalable/apps/download-npo-gui.svg
download_npo-2.9.1.dist-info/LICENSE
download_npo-2.9.1.dist-info/METADATA
download_npo-2.9.1.dist-info/WHEEL
download_npo-2.9.1.dist-info/top_level.txt
download_npo-2.9.1.dist-info/RECORD
